[
    {
        "args": {
            "train_data": "training.mat",
            "train_size": 0.6,
            "val_samples": 400,
            "test_samples": 400,
            "train_labels": "training_labels.mat",
            "model_type": "Transformer",
            "batch_size": 32,
            "epochs": 100,
            "lr": 0.001,
            "lr_decay": false,
            "patience": 10,
            "augment": true,
            "results_dir": "saved_results",
            "results_name": "Transformer_20230420_163508.json",
            "save_name": "Transformer_20230420_163508.h5",
            "save_dir": "saved_models",
            "comment": ""
        },
        "results": {
            "loss": 0.6117886900901794,
            "accuracy": 0.7720000147819519,
            "precision": 0.8191068172454834,
            "recall": 0.7285000085830688
        }
    }
]